punchcard/__init__.py
punchcard/module.py
punchcard/period.py
punchcard/screens.py
punchcard/state.py
project_rigor_punchcard-0.0.3.dist-info/METADATA
project_rigor_punchcard-0.0.3.dist-info/WHEEL
project_rigor_punchcard-0.0.3.dist-info/top_level.txt
project_rigor_punchcard-0.0.3.dist-info/RECORD
