Metadata-Version: 2.4
Name: project-rigor-punchcard
Version: 0.0.3
Summary: A Punchcard module for Project RIGOR
Author: jarvick257
License-Expression: MIT
Project-URL: Homepage, https://github.com/jarvick257/rigor-punchcard
Classifier: Programming Language :: Python :: 3
Classifier: Operating System :: OS Independent
Requires-Python: >=3.9
